Metadata-Version: 1.2
Name: text-to-image
Version: 0.0.4
Summary: Convert your text to a grayscale image and back.
Home-page: https://github.com/akapila011/Text-to-Image
Author: Abhishek Kapila
Author-email: akapila011@gmail.com
License: MIT
Keywords: Graphics Encoding Decoding Stenography
Platform: UNKNOWN
Classifier: Development Status :: 3 - Alpha
Classifier: Intended Audience :: Developers
Classifier: Intended Audience :: End Users/Desktop
Classifier: Topic :: Scientific/Engineering :: Visualization
Classifier: Topic :: Security :: Cryptography
Classifier: Topic :: Multimedia :: Graphics
Classifier: Programming Language :: Python :: 3
Classifier: Natural Language :: English
Requires-Python: >=3
